Workbook

Sheet README
A1: Cyber Risk-to-Value Model
A2: PURPOSE | B2: Translate cyber threats into financial numbers using a FAIR-inspired Monte Carlo simulation. All figures are synthetic / dummy data for learning purposes.
A4: WHAT IS FAIR? | B4: FAIR = Factor Analysis of Information Risk. It separates risk into two dimensions: • HOW OFTEN does a bad event happen? (Frequency) • HOW MUCH does it cost when it does? (Magnitude)
A6: WHAT IS MONTE CARLO? | B6: A technique that repeats a random experiment thousands of times to build a probability distribution of outcomes — like rolling dice 10,000 times to understand the full range of possible results.
A8: TAB GUIDE | B8: Tab | C8: What's in it
B9: INPUTS | C9: Assumptions you can change: frequency, magnitude, control costs
B10: SCENARIOS | C10: 3 risk scenarios with their statistical parameters (λ, μ, σ)
B11: SIMULATION | C11: 500 Monte Carlo iterations — each row is one simulated year
B12: OUTPUTS | C12: Summary statistics: mean, median, percentiles, ROI
B13: SENSITIVITY | C13: A grid showing how outcomes shift if frequency/magnitude assumptions change
A15: COLOR CODE | B15: Blue text → Input you can change
B16: Black text → Formula calculated by Excel
B17: Green text → Formula pulling from another tab
B18: Yellow bg → Key cell to pay attention to
A20: HOW TO USE | B20: Step 1: Read SCENARIOS to understand the risk assumptions.
B21: Step 2: Go to INPUTS and change the yellow cells to try different assumptions.
B22: Step 3: Watch OUTPUTS update automatically — all tabs are linked by formula.
B23: Step 4: Use SENSITIVITY to explore 'what if' scenarios.

Sheet INPUTS
A1: INPUTS — Change the blue/yellow cells to update the whole model
A3: ── SIMULATION SETTINGS ──
A4: Number of Iterations | B4: 500 | C4: ← INPUTS!B4 | D4: More iterations = smoother distribution (try 1000). Re-run simulation to refresh.
A5: Random Seed | B5: 42 | D5: Fixing the seed makes results reproducible. Change to any integer for a new draw.
A7: ── CONTROL ASSUMPTIONS ──
A8: Frequency Reduction % (e.g. MFA, Phishing Training) | B8: 0.3 | C8: ← INPUTS!B8 | D8: Controls reduce how OFTEN an event occurs. 30% means attacks happen 30% less.
A9: Magnitude Reduction % (e.g. IR Retainer, Backups) | B9: 0.35 | C9: ← INPUTS!B9 | D9: Controls reduce how MUCH an event costs. 35% means losses are 35% smaller.
A11: ── CONTROL COSTS ──
A12: Cost: Frequency Control (e.g. MFA + training programme) | B12: 1000000 | D12: Annual cost of prevention-focused investments.
A13: Cost: Magnitude Control (e.g. IR retainer + backup solution) | B13: 1500000 | D13: Annual cost of response/recovery-focused investments.
A14: Cost: Both Controls Combined (assumes synergy savings) | B14: 2300000 | D14: Combined cost — less than the sum because some tools serve both purposes.

Sheet SCENARIOS
A1: SCENARIOS — Risk parameters for each threat (edit blue cells)
A2: Scenario | B2: λ (Lambda) | C2: μ (Mu) | D2: σ (Sigma) | E2: Explanation
B3: Avg events/year (Poisson λ) | C3: Avg log-loss (e.g. 14 → ~$1.2M) | D3: Spread of loss (higher = wilder swings)
A4: Ransomware | B4: 0.6 | C4: 14 | D4: 1.2 | E4: λ=0.6 → expect ~1 attack every 1.7 years. e^14 ≈ $1.2M median loss, but σ=1.2 means a bad event could be 10× that.
A5: Business Email Compromise (BEC) | B5: 0.9 | C5: 12.5 | D5: 0.8 | E5: λ=0.9 → nearly 1 BEC attempt per year. Losses are smaller (e^12.5 ≈ $270K) but very consistent (low σ).
A6: Data Exfiltration | B6: 0.3 | C6: 15 | D6: 1 | E6: λ=0.3 → rare, roughly 1 in 3 years. But e^15 ≈ $3.3M median loss and moderate spread make tail risk significant.
A8: HOW THE MATH WORKS — formulas Excel uses in the SIMULATION tab
A9: Step | B9: Formula / Concept | C9: Plain English
A10: 1. Did an event occur? | B10: IF(RAND() < lambda, "Yes", "No") [shown as text example only] | C10: RAND() gives a random number 0–1. If it's below λ (the annual probability), an event happened this year.
A11: 2. How many events? | B11: Approx. Poisson via -LN(RAND())/λ [in SIMULATION col C/F/I] | C11: A Poisson draw. When λ is small this is usually 0 or 1.
A12: 3. How big was the loss? | B12: EXP( mu + sigma * NORM.S.INV(RAND()) ) [text example only] | C12: Lognormal draw: μ is the average log-loss, σ controls the spread. EXP() converts back to dollars.
A13: 4. Total loss this year? | B13: event_count x individual_loss [text example only] | C13: Multiply # of events by each event's cost. Most years = $0 (no event).
A14: 5. With frequency control? | B14: Use λ × (1 - Freq_Reduction) in Step 2 | C14: If λ=0.6 and reduction=30%, new λ=0.42. Events happen less often.
A15: 6. With magnitude control? | B15: Multiply loss from Step 3 by (1 - Mag_Reduction) | C15: If loss=$1M and reduction=35%, controlled loss=$650K.

Sheet SIMULATION
A1: SIMULATION — Each row is one randomly simulated year (500 iterations)
A2: Iteration # | B2: BASELINE (no controls) | F2: FREQUENCY CONTROL (reduce how often) | J2: MAGNITUDE CONTROL (reduce how much) | N2: BOTH CONTROLS
A3: # | B3: Ransomware | C3: BEC | D3: Exfil | E3: TOTAL ($) | F3: Ransomware | G3: BEC | H3: Exfil | I3: TOTAL ($) | J3: Ransomware | K3: BEC | L3: Exfil | M3: TOTAL ($) | N3: Ransomware | O3: BEC | P3: Exfil | Q3: TOTAL ($)
A4: → Row # | B4: Formula template: =IF(RAND()<SCENARIOS!B4, EXP(SCENARIOS!C4+SCENARIOS!D4*NORM.S.INV(RAND())), 0) | C4: Formula template: Same for BEC (row 5) | D4: Formula template: Same for Exfil (row 6) | E4: Formula template: =SUM(B5:D5) — total loss this year | F4: Formula template: =IF(RAND()<SCENARIOS!B4*(1-INPUTS!B8), EXP(SCENARIOS!C4+SCENARIOS!D4*NORM.S.INV(RAND())), 0) | G4: Formula template: Same, BEC freq reduced | H4: Formula template: Same, Exfil freq reduced | I4: Formula template: =SUM(F5:H5) | J4: Formula template: =IF(RAND()<SCENARIOS!B4, EXP(SCENARIOS!C4+SCENARIOS!D4*NORM.S.INV(RAND()))*(1-INPUTS!B9), 0) | K4: Formula template: Same, BEC mag reduced | L4: Formula template: Same, Exfil mag reduced | M4: Formula template: =SUM(J5:L5) | N4: Formula template: =IF(RAND()<SCENARIOS!B4*(1-INPUTS!B8), EXP(SCENARIOS!C4+SCENARIOS!D4*NORM.S.INV(RAND()))*(1-INPUTS!B9), 0) | O4: Formula template: BEC both | P4: Formula template: Exfil both | Q4: Formula template: =SUM(N5:P5)
A5: 1 | B5: 3111370 | C5: 216669.84 | D5: 0 | E5: =B5+C5+D5 -> 3328039.8 | F5: 0 | G5: 0 | H5: 0 | I5: =F5+G5+H5 -> 0 | J5: 908762.46 | K5: 0 | L5: 0 | M5: =J5+K5+L5 -> 908762.46 | N5: 1164729.1 | O5: 0 | P5: 0 | Q5: =N5+O5+P5 -> 1164729.1
A6: 2 | B6: 0 | C6: 0 | D6: 2792809.5 | E6: =B6+C6+D6 -> 2792809.5 | F6: 0 | G6: 0 | H6: 955883.67 | I6: =F6+G6+H6 -> 955883.67 | J6: 6851740.2 | K6: 1004604.2 | L6: 0 | M6: =J6+K6+L6 -> 7856344.5 | N6: 854187.76 | O6: 422975.3 | P6: 0 | Q6: =N6+O6+P6 -> 1277163.1
A7: 3 | B7: 207904.75 | C7: 0 | D7: 0 | E7: =B7+C7+D7 -> 207904.75 | F7: 0 | G7: 0 | H7: 0 | I7: =F7+G7+H7 -> 0 | J7: 155043.68 | K7: 0 | L7: 0 | M7: =J7+K7+L7 -> 155043.68 | N7: 0 | O7: 0 | P7: 0 | Q7: =N7+O7+P7 -> 0
A8: 4 | B8: 0 | C8: 0 | D8: 0 | E8: =B8+C8+D8 -> 0 | F8: 0 | G8: 402139.43 | H8: 0 | I8: =F8+G8+H8 -> 402139.43 | J8: 0 | K8: 605155.92 | L8: 0 | M8: =J8+K8+L8 -> 605155.92 | N8: 501554.92 | O8: 42540.74 | P8: 0 | Q8: =N8+O8+P8 -> 544095.66
A9: 5 | B9: 0 | C9: 0 | D9: 0 | E9: =B9+C9+D9 -> 0 | F9: 3109387.7 | G9: 0 | H9: 1852901.9 | I9: =F9+G9+H9 -> 4962289.7 | J9: 94813.38 | K9: 514623.87 | L9: 6664581.8 | M9: =J9+K9+L9 -> 7274019.1 | N9: 0 | O9: 0 | P9: 0 | Q9: =N9+O9+P9 -> 0
A10: 6 | B10: 0 | C10: 812782.29 | D10: 0 | E10: =B10+C10+D10 -> 812782.29 | F10: 0 | G10: 244435.04 | H10: 0 | I10: =F10+G10+H10 -> 244435.04 | J10: 532539.8 | K10: 94452.13 | L10: 0 | M10: =J10+K10+L10 -> 626991.93 | N10: 0 | O10: 150861.51 | P10: 3704539.4 | Q10: =N10+O10+P10 -> 3855400.9
A11: 7 | B11: 0 | C11: 164471.06 | D11: 0 | E11: =B11+C11+D11 -> 164471.06 | F11: 0 | G11: 0 | H11: 0 | I11: =F11+G11+H11 -> 0 | J11: 1968831.8 | K11: 45353.37 | L11: 0 | M11: =J11+K11+L11 -> 2014185.1 | N11: 0 | O11: 0 | P11: 1388738.4 | Q11: =N11+O11+P11 -> 1388738.4
A12: 8 | B12: 2483486.1 | C12: 0 | D12: 0 | E12: =B12+C12+D12 -> 2483486.1 | F12: 0 | G12: 240200.51 | H12: 1774404 | I12: =F12+G12+H12 -> 2014604.6 | J12: 1263120.5 | K12: 327035.88 | L12: 0 | M12: =J12+K12+L12 -> 1590156.4 | N12: 0 | O12: 336113.1 | P12: 0 | Q12: =N12+O12+P12 -> 336113.1
A13: 9 | B13: 0 | C13: 0 | D13: 0 | E13: =B13+C13+D13 -> 0 | F13: 0 | G13: 0 | H13: 0 | I13: =F13+G13+H13 -> 0 | J13: 1790227.6 | K13: 0 | L13: 0 | M13: =J13+K13+L13 -> 1790227.6 | N13: 0 | O13: 187125.32 | P13: 4278194.8 | Q13: =N13+O13+P13 -> 4465320.1
A14: 10 | B14: 2672506.4 | C14: 300164.98 | D14: 0 | E14: =B14+C14+D14 -> 2972671.4 | F14: 1760354.8 | G14: 322477.24 | H14: 0 | I14: =F14+G14+H14 -> 2082832 | J14: 0 | K14: 0 | L14: 0 | M14: =J14+K14+L14 -> 0 | N14: 0 | O14: 0 | P14: 0 | Q14: =N14+O14+P14 -> 0
A15: 11 | B15: 6261186.3 | C15: 451191.8 | D15: 0 | E15: =B15+C15+D15 -> 6712378.1 | F15: 0 | G15: 0 | H15: 0 | I15: =F15+G15+H15 -> 0 | J15: 786853.95 | K15: 0 | L15: 20565794 | M15: =J15+K15+L15 -> 21352648 | N15: 0 | O15: 343516.61 | P15: 0 | Q15: =N15+O15+P15 -> 343516.61
A16: 12 | B16: 0 | C16: 0 | D16: 0 | E16: =B16+C16+D16 -> 0 | F16: 0 | G16: 1450848.1 | H16: 0 | I16: =F16+G16+H16 -> 1450848.1 | J16: 0 | K16: 29452.18 | L16: 1878516.3 | M16: =J16+K16+L16 -> 1907968.4 | N16: 0 | O16: 609448.52 | P16: 0 | Q16: =N16+O16+P16 -> 609448.52
... A504: 500 | B504: 4757713.1 | C504: 256479.63 | D504: 0 | E504: =B504+C504+D504 -> 5014192.8 | F504: 0 | G504: 0 | H504: 0 | I504: =F504+G504+H504 -> 0 | J504: 0 | K504: 565776.33 | L504: 1360724.9 | M504: =J504+K504+L504 -> 1926501.2 | N504: 0 | O504: 0 | P504: 0 | Q504: =N504+O504+P504 -> 0

Sheet OUTPUTS
A1: OUTPUTS — All numbers are formulas pulling from SIMULATION
A2: Metric | B2: Baseline | C2: Frequency Control | D2: Magnitude Control | E2: Both Controls | F2: What does this mean?
B3: =AVERAGE(SIMULATION!E5:E504) -> 2986291.9 | C3: =AVERAGE(SIMULATION!I5:I504) -> 1995797.9 | D3: =AVERAGE(SIMULATION!M5:M504) -> 2198550.3 | E3: =AVERAGE(SIMULATION!Q5:Q504) -> 1789145.6 | F3: ← Formula pattern for each cell in the MEAN row
A4: Mean (Expected Annual Loss) | B4: =AVERAGE(SIMULATION!E5:E504) -> 2986291.9 | C4: =AVERAGE(SIMULATION!I5:I504) -> 1995797.9 | D4: =AVERAGE(SIMULATION!M5:M504) -> 2198550.3 | E4: =AVERAGE(SIMULATION!Q5:Q504) -> 1789145.6 | F4: The average loss across all 500 simulated years. Think of this as your 'budget' for cyber losses.
A5: Median (P50 — half above, half below) | B5: =MEDIAN(SIMULATION!E5:E504) -> 931901.31 | C5: =MEDIAN(SIMULATION!I5:I504) -> 493216.72 | D5: =MEDIAN(SIMULATION!M5:M504) -> 917714.06 | E5: =MEDIAN(SIMULATION!Q5:Q504) -> 415629.61 | F5: In 50% of simulated years, loss was below this. Often much lower than the mean because of rare large events.
A6: P75 (75th percentile) | B6: =PERCENTILE(SIMULATION!E5:E504, 0.75) -> 3589412.4 | C6: =PERCENTILE(SIMULATION!I5:I504, 0.75) -> 2324461.5 | D6: =PERCENTILE(SIMULATION!M5:M504, 0.75) -> 2375615.7 | E6: =PERCENTILE(SIMULATION!Q5:Q504, 0.75) -> 1914322.6 | F6: In 75% of years, losses were at or below this level.
A7: P90 | B7: =PERCENTILE(SIMULATION!E5:E504, 0.9) -> 8507880.7 | C7: =PERCENTILE(SIMULATION!I5:I504, 0.9) -> 5375132 | D7: =PERCENTILE(SIMULATION!M5:M504, 0.9) -> 5378029.2 | E7: =PERCENTILE(SIMULATION!Q5:Q504, 0.9) -> 4636230.8 | F7: Loss level exceeded only 1 in 10 years. A common risk appetite threshold.
A8: P95 — 'Value at Risk' | B8: =PERCENTILE(SIMULATION!E5:E504, 0.95) -> 12723448 | C8: =PERCENTILE(SIMULATION!I5:I504, 0.95) -> 8812967.1 | D8: =PERCENTILE(SIMULATION!M5:M504, 0.95) -> 8884921.3 | E8: =PERCENTILE(SIMULATION!Q5:Q504, 0.95) -> 7486853 | F8: Exceeded only 1 in 20 years. The 'tail risk' figure most executives focus on.
A9: P99 — Worst-case tail | B9: =PERCENTILE(SIMULATION!E5:E504, 0.99) -> 26630612 | C9: =PERCENTILE(SIMULATION!I5:I504, 0.99) -> 15205911 | D9: =PERCENTILE(SIMULATION!M5:M504, 0.99) -> 18948643 | E9: =PERCENTILE(SIMULATION!Q5:Q504, 0.99) -> 17687212 | F9: Only exceeded in 1 in 100 years — your 'black swan' estimate.
A10: Std Dev (Volatility) | B10: =STDEV(SIMULATION!E5:E504) -> 5006903.7 | C10: =STDEV(SIMULATION!I5:I504) -> 3690574.7 | D10: =STDEV(SIMULATION!M5:M504) -> 3909074.1 | E10: =STDEV(SIMULATION!Q5:Q504) -> 3840867.6 | F10: How widely spread the results are. High std dev = unpredictable year-to-year losses.
A12: RETURN ON INVESTMENT ANALYSIS
A13: Control Cost (from INPUTS) | C13: =INPUTS!B12 -> 1000000 | D13: =INPUTS!B13 -> 1500000 | E13: =INPUTS!B14 -> 2300000 | F13: Annual cost of each control investment — pulled directly from the INPUTS tab.
A14: Expected Savings vs Baseline | C14: =B4-C4 -> 990493.97 | D14: =B4-D4 -> 787741.59 | E14: =B4-E4 -> 1197146.3 | F14: How much lower is the mean loss compared to Baseline? Formula: Baseline Mean − This Case Mean.
A15: Simple ROI (Savings ÷ Cost) | C15: =C14/C13 -> 0.99049397 | D15: =D14/D13 -> 0.52516106 | E15: =E14/E13 -> 0.5204984 | F15: If ROI > 1.0×, the expected savings exceed the cost. <1.0× means cost outweighs benefit at this confidence level.

Sheet SENSITIVITY
A1: SENSITIVITY — How does P95 loss change as we vary frequency & magnitude reductions?
A2: HOW TO READ THIS TABLE
A3: Each cell shows the estimated P95 loss (95th percentile) for that combination of Frequency Reduction % (columns) and Magnitude Reduction % (rows).
A4: The highlighted diagonal shows the current INPUTS assumption. Green = better than baseline. The further down-right, the more protection.
A5: Mag Reduction ↓ / Freq Reduction → | C5: 0.1 | D5: 0.2 | E5: 0.3 | F5: 0.4 | G5: 0.5
A6: 0.1 | C6: 9572792.3 | D6: 10511826 | E6: 9446306.4 | F6: 8566629.6 | G6: 6106007.1
A7: 0.2 | C7: 8509148.7 | D7: 9343845.3 | E7: 8396716.8 | F7: 7614781.9 | G7: 5427561.9
A8: 0.3 | C8: 7445505.1 | D8: 8175864.6 | E8: 7347127.2 | F8: 6662934.1 | G8: 4749116.6
A9: 0.4 | C9: 6381861.5 | D9: 7007883.9 | E9: 6297537.6 | F9: 5711086.4 | G9: 4070671.4
A10: 0.5 | C10: 5318217.9 | D10: 5839903.3 | E10: 5247948 | F10: 4759238.7 | G10: 3392226.2
A12: LEGEND
A13: Dark green | C13: P95 is < 55% of baseline — very strong protection
A14: Light green | C14: P95 is 55–70% of baseline — solid reduction
A15: Yellow | C15: P95 is 70–85% of baseline — modest reduction
A16: Red | C16: P95 is > 85% of baseline — minimal impact
A17: Bold border | C17: Closest match to your current INPUTS assumptions (Freq=30%, Mag=35%)

Sheet Next Steps
A2: Here are the main directions you can go with this model:
A3: Risk storytelling for executives
A4: "Our expected annual cyber loss is $X, but in a bad year (P95) it could reach $Y" — the classic risk narrative
A5: Compare the four scenarios side-by-side to show what different control investments are worth in dollar terms
A6: Break down which of the three threats (Ransomware, BEC, Exfiltration) is driving the most risk
A8: Investment decisions
A9: The ROI tab already shows simple payback — you can extend this to show break-even years
A10: "At what control cost does the investment stop making financial sense?" (back-solve the ROI)
A11: Compare frequency vs. magnitude controls — which type of spending gives better return?
A13: Sensitivity & scenario analysis
A14: Use the sensitivity grid to answer "what if our security controls are only 50% as effective as assumed?"
A15: Stress-test with higher λ values (e.g. if threat landscape worsens)
... A75: Regulatory and audit contexts often require explainability — a human-readable Excel formula is sometimes more defensible than an ML model, even if the ML model is more accurate
